ffmpeg_wrapper.py
utils.py
vidcompiler.py
vidcompiler-1.15.dist-info/METADATA
vidcompiler-1.15.dist-info/WHEEL
vidcompiler-1.15.dist-info/top_level.txt
vidcompiler-1.15.dist-info/RECORD
