Metadata-Version: 2.1
Name: vidcompiler
Version: 1.15
Summary: A Des of vidcompiler
Home-page: https://github.com/vtandroid/dokr
Author: Thanh Hoa
Author-email: thanhhoakhmt1@gmail.com
License: UNKNOWN
Platform: UNKNOWN
Classifier: Programming Language :: Python :: 3
Classifier: License :: OSI Approved :: MIT License
Classifier: Operating System :: OS Independent
